money2float.py
money2float-0.6.dist-info/METADATA
money2float-0.6.dist-info/WHEEL
money2float-0.6.dist-info/top_level.txt
money2float-0.6.dist-info/RECORD
