Metadata-Version: 2.1
Name: money2float
Version: 0.6
Summary: Helper function to convert money to float
Home-page: https://github.com/hudgeon
Author: Hudge
Author-email: doug@mybusinessautomated.com
License: UNKNOWN
Platform: UNKNOWN
Classifier: Programming Language :: Python :: 3
Classifier: License :: OSI Approved :: MIT License
Classifier: Operating System :: OS Independent
